bee_scheduler/__init__.py
bee_scheduler/scheduler.py
bee_scheduler-1.0.2.dist-info/METADATA
bee_scheduler-1.0.2.dist-info/WHEEL
bee_scheduler-1.0.2.dist-info/licenses/LICENSE
bee_scheduler-1.0.2.dist-info/RECORD
