Metadata-Version: 2.4
Name: bee-scheduler
Version: 1.0.2
Summary: A scheduling library for beeminder.
Project-URL: Homepage, https://github.com/maxtrussell/bee-scheduler
Project-URL: Issues, https://github.com/maxtrussell/bee-scheduler/issues
Author-email: Max Trussell <maxtrussell@gmail.com>
License-Expression: MIT
License-File: LICENSE
Classifier: Operating System :: OS Independent
Classifier: Programming Language :: Python :: 3
Requires-Python: >=3.8
Requires-Dist: requests
